etc/schindler/visualgc-remote-control.yaml
visualgc_remote_control/__init__.py
visualgc_remote_control/__main__.py
visualgc_remote_control/enterprise.py
visualgc_remote_control/main.py
visualgc_remote_control/remote_commands.py
visualgc_remote_control/remote_control_app.py
visualgc_remote_control/visualgc_remote_control.py
visualgc_remote_control/au3_scripts/__init__.py
visualgc_remote_control/au3_scripts/accept_certificate.au3
visualgc_remote_control/au3_scripts/test.txt
visualgc_remote_control/au3_scripts/test_trip_101.au3
visualgc_remote_control-0.0.9.dist-info/METADATA
visualgc_remote_control-0.0.9.dist-info/WHEEL
visualgc_remote_control-0.0.9.dist-info/entry_points.txt
visualgc_remote_control-0.0.9.dist-info/top_level.txt
visualgc_remote_control-0.0.9.dist-info/RECORD
