Metadata-Version: 2.1
Name: visualgc-remote-control
Version: 0.0.9
Summary: visualgc-remote-control
Home-page: https://luism.co
Author: Luis Coelho
Author-email: luis.coelho.720813@gmail.com
License: Apache v2
Keywords: VisualGC,Configuration,REST
Platform: UNKNOWN
Requires-Dist: Flask (>=2.2.2)
